[1,["ecpdLyjvZBwrvm+cedCcQy","1308310f1","52I9CBioNJS5Lo389Bfti3","66QnIvFNNLJLXSK8Zq/Qo+"],["node","root","_spriteFrame","_textureSetter","_parent","data"],[["cc.Node",["_name","_prefab","_components","_contentSize","_parent","_trs","_children","_anchorPoint"],2,4,9,5,1,7,12,5],["cc.Sprite",["_sizeMode","_type","_name","node","_materials","_spriteFrame"],0,1,3,6],"cc.SpriteFrame",["cc.Prefab",["_name"],2],["cc.PrefabInfo",["fileId","root"],2,1],["7531efetpFFoa/7yUZuv/Bt",["node"],3,1]],[[4,0,1,2],[3,0,2],[0,0,6,2,1,3,7,2],[0,0,4,1,5,2],[0,0,4,2,1,3,5,2],[1,1,0,3,4,5,3],[1,2,0,3,4,5,3],[5,0,1]],[[[{"name":"加好友","rect":[345,408,85,85],"offset":[0,0],"originalSize":[85,85],"capInsets":[0,0,0,0]}],[2],0,[0],[3],[1]],[[[1,"FriendItem"],[2,"FriendItem",[[-4,[3,"icon",-6,[0,"d7Q5hwQohOuKOfT2NlsTbJ",-5],[270,-48,0,0,0,0,1,1,1,1]]],1,4],[[5,1,0,-2,[2],3],[7,-3]],[0,"28B0ezn85PCohyniHHxFJ+",-1],[5,476,96],[0,0,1]],[4,"add_",1,[[6,"add_<Sprite>",2,-7,[0],1]],[0,"ddXcIXw6tBhLN3eG7yMEk7",1],[5,85,85],[48,-48,0,0,0,0,1,1,1,1]]],0,[0,1,1,0,0,1,0,0,1,0,-1,2,0,1,1,0,4,1,0,0,2,0,5,1,7],[0,0,0,0],[-1,2,-1,2],[0,2,0,3]]]]